.gitignore
.pre-commit-config.yaml
.pylintrc
CODE_OF_CONDUCT.md
LICENSE
README.rst
README.rst.license
commedagh_pypi_version_testing.py
pyproject.toml
requirements.txt
setup.py
.github/PULL_REQUEST_TEMPLATE/adafruit_circuitpython_pr.md
.github/workflows/build.yml
.github/workflows/failure-help-text.yml
.github/workflows/release.yml
LICENSES/CC-BY-4.0.txt
LICENSES/MIT.txt
LICENSES/Unlicense.txt
commedagh_circuitpython_pypi_version_testing.egg-info/PKG-INFO
commedagh_circuitpython_pypi_version_testing.egg-info/SOURCES.txt
commedagh_circuitpython_pypi_version_testing.egg-info/dependency_links.txt
commedagh_circuitpython_pypi_version_testing.egg-info/requires.txt
commedagh_circuitpython_pypi_version_testing.egg-info/top_level.txt
commedagh_pypi_version_testing/__init__.py
examples/pypi-version-testing_simpletest.py