Metadata-Version: 2.1
Name: commedagh-circuitpython-pypi-version-testing
Version: 0.0.1a16.dev0
Summary: testing pypi versioning
Home-page: https://github.com/lesamouraipourpre/Commedagh_CircuitPython_pypi-version-testing.git
Author: James Carr
Author-email: lesamouraipourpre@gmail.com
License: MIT
Keywords: adafruit blinka circuitpython micropython pypi-version-testing test pypi version
Platform: UNKNOWN
Classifier: Development Status :: 3 - Alpha
Classifier: Intended Audience :: Developers
Classifier: Topic :: Software Development :: Libraries
Classifier: Topic :: System :: Hardware
Classifier: License :: OSI Approved :: MIT License
Classifier: Programming Language :: Python :: 3
Classifier: Programming Language :: Python :: 3.4
Classifier: Programming Language :: Python :: 3.5
